{"path": "C:\\Users\\Rachneet Kaur\\Box\\Gait Video Project\\GaitVideoData\\video\\",
"data_path": "downsampled_strides\\", 
"labels_file": "labels.csv",
"results_path": "C:\\Users\\Rachneet Kaur\\Box\\Gait Video Project\\DLresults\\",
"model_path": "RNN\\",
"model": "RNN",
"prefix_name": "rnn_try_task_gen",
"save_results": true,
"train_framework": "W",
"test_framework": "WT",
"framework": "WtoWT",       
"shuffle":true,
"num_workers":0,
"behavior": "train",
"re_train_epochs": 5,
"saved_model_path": "cnn1d_try_2021_01_26-19_11_02_951362\\",
"datastream": "All",
"param_batch_size": [100],
"param_lr": [0.0001],
"param_optimizer": ["torch.optim.Adam"],
"param_module__in_chans": [36],
"param_module__num_classes": [3],
"param_module__dropout": [0.3],
"param_module__hidden_size1": [30],
"param_module__num_layers1": [3],
"param_module__hidden_size2": [20],
"param_module__num_layers2": [2],
"param_module__bidirectional": [false],
"param_module__pre_out": [50],
"param_module__single_layer": [false],
"param_module__linear_size": [1],
"param_module__use_layernorm": [false]
}
